{
  "authors": [],
  "doi": "",
  "publication_date": "2021-05-08",
  "id": "FR108503",
  "url": "https://base-donnees-publique.medicaments.gouv.fr/affichageDoc.php?specid=64821401&typedoc=N",
  "source": "Ministère des Solidarités et de la Santé",
  "source_url": "https://base-donnees-publique.medicaments.gouv.fr/",
  "licence": "CC-BY-NC",
  "language": "fr",
  "type": "other",
  "description": "patient information leaflets for medicines",
  "text": "LORAZEPAM MYLAN 2,5 mg, comprimé pelliculé sécable Lorazépam Encadré Veuillez lire attentivement cette notice avant de prendre ce médicament car elle contient des informations importantes pour vous. · Gardez cette notice. Vous pourriez avoir besoin de la relire. · Si vous avez d’autres questions, interrogez votre médecin, votre pharmacien ou votre infirmier/ère. · Ce médicament vous a été personnellement prescrit. Ne le donnez pas à d’autres personnes. Il pourrait leur être nocif, même si les signes de leur maladie sont identiques aux vôtres. · Si vous ressentez un quelconque effet indésirable, parlez-en à votre médecin, votre pharmacien ou votre infirmier/ère. Ceci s’applique aussi à tout effet indésirable qui ne serait pas mentionné dans cette notice. Voir rubrique 4. Que contient cette notice ? 1. Qu'est-ce que LORAZEPAM MYLAN 2,5 mg, comprimé pelliculé sécable et dans quels cas est-il utilisé ? 2. Quelles sont les informations à connaître avant de prendre LORAZEPAM MYLAN 2,5 mg, comprimé pelliculé sécable ? 3. Comment prendre LORAZEPAM MYLAN 2,5 mg, comprimé pelliculé sécable ? 4. Quels sont les effets indésirables éventuels ? 5. Comment conserver LORAZEPAM MYLAN 2,5 mg, comprimé pelliculé sécable ? 6. Contenu de l’emballage et autres informations. 1. QU’EST-CE QUE LORAZEPAM MYLAN 2,5 mg, comprimé pelliculé sécable ET DANS QUELS CAS EST-IL UTILISE ? Classe pharmacothérapeutique : anxiolytiques - code ATC : N05BA06. Ce médicament est apparenté aux benzodiazépines. Ce médicament est préconisé dans le traitement de l'anxiété lorsque celle-ci s'accompagne de troubles gênants, ou en prévention et/ou traitement des manifestations liées à un sevrage alcoolique. 2. QUELLES SONT LES INFORMATIONS A CONNAITRE AVANT DE PRENDRE LORAZEPAM MYLAN 2,5 mg, comprimé pelliculé sécable ? Ne prenez jamais LORAZEPAM MYLAN 2,5 mg, comprimé pelliculé sécable : · si vous êtes allergique (hypersensible) au lorazépam ou à cette classe de produits ou à l’un des autres composants contenus dans ce médicament, mentionnés dans la rubrique 6, · si vous avez une insuffisance respiratoire grave, · si vous avez un syndrome d'apnée du sommeil (pauses respiratoires pendant le sommeil), · si vous avez une insuffisance hépatique grave, · si vous êtes atteint d’une myasthénie (maladie caractérisée par une tendance excessive à la fatigue musculaire). EN CAS DE DOUTE, IL EST INDISPENSABLE DE DEMANDER L'AVIS DE VOTRE MEDECIN OU DE VOTRE PHARMACIEN. Avertissements et précautions Adressez-vous à votre médecin, pharmacien ou votre infirmier/ère avant de prendre LORAZEPAM MYLAN 2,5 mg, comprimé pelliculé sécable. Mises en garde Si une perte d'efficacité survient lors de l'utilisation répétée du médicament, n'augmentez pas la dose. Risque de DEPENDANCE : ce traitement peut entraîner, surtout en cas d'utilisation prolongée, un état de dépendance physique et psychique. Divers facteurs semblent favoriser la survenue de la dépendance : · durée du traitement, · dose, · antécédents d'autres dépendances médicamenteuses ou non, y compris alcoolique. La dépendance peut survenir même en l'absence de ces facteurs favorisants. Pour plus d'information, parlez-en à votre médecin ou à votre pharmacien. Arrêter BRUTALEMENT ce traitement peut provoquer l'apparition d'un phénomène de SEVRAGE. Celui-ci se caractérise par l'apparition, en quelques heures ou en quelques jours, de signes tels que anxiété importante, insomnie, douleurs musculaires, mais on peut observer également une agitation, une irritabilité, des maux de tête, un engourdissement ou des picotements des extrémités, une sensibilité anormale au bruit, à la lumière ou aux contacts physiques, etc... Les modalités de l'arrêt du traitement doivent être définies avec votre médecin. La diminution très PROGRESSIVE des doses et l'espacement des prises représentent la meilleure prévention de ce phénomène de sevrage. Cette période sera d'autant plus longue que le traitement aura été prolongé. Malgré la décroissance progressive des doses, un phénomène de REBOND sans gravité peut se produire, avec réapparition TRANSITOIRE des symptômes (anxiété) qui avaient justifié la mise en route du traitement. Des troubles de mémoire ainsi que des altérations des fonctions psychomotrices sont susceptibles d'apparaître dans les heures qui suivent la prise du médicament. Chez certains sujets, ce médicament peut provoquer des réactions contraires à l'effet recherché : insomnie, cauchemars, agitation, nervosité, euphorie ou irritabilité, tension, modifications de la conscience, voire des comportements potentiellement dangereux (agressivité envers soi-même ou son entourage, ainsi que des troubles du comportement et des actes automatiques). Si une ou plusieurs de ces réactions surviennent, contactez le plus rapidement possible votre médecin. Les benzodiazépines et produits apparentés doivent être utilisés avec prudence chez le sujet âgé, en raison du risque de somnolence et/ou de relâchement musculaire qui peuvent favoriser les chutes, avec des conséquences souvent graves dans cette population. Précautions d'emploi Ce traitement médicamenteux ne peut à lui seul résoudre les difficultés liées à une anxiété. Il convient de demander conseil à votre médecin. Il vous indiquera les conduites pouvant aider à la lutte contre l'anxiété. La prise de ce médicament nécessite un suivi médical renforcé notamment en cas d'insuffisance rénale, de maladie chronique du foie, d'alcoolisme et d'insuffisance respiratoire. Ce médicament ne traite pas la dépression. Chez le sujet présentant une dépression, il ne doit pas être utilisé seul car il laisserait la dépression évoluer pour son propre compte avec persistance ou majoration du risque suicidaire. La prise d'alcool est formellement déconseillée pendant la durée du traitement. Adressez-vous à votre médecin ou à votre pharmacien avant de prendre LORAZEPAM MYLAN. Enfants et adolescents Sans objet. Autres médicaments et LORAZEPAM MYLAN 2,5 mg, comprimé pelliculé sécable Informez votre médecin ou pharmacien si vous prenez, avez récemment pris ou pourriez prendre tout autre médicament, y compris un médicament obtenu sans ordonnance. L’utilisation concomitante de LORAZEPAM MYLAN 2,5 mg, comprimé pelliculé sécable et d’opioïdes (médicaments antidouleur forts, médicaments utilisés en traitement de substitution et certains médicaments contre la toux) accroît le risque de somnolence, de difficultés à respirer (dépression respiratoire), de coma et peut mettre en jeu le pronostic vital. Pour cette raison, l’utilisation concomitante ne doit être envisagée que quand d’autres options thérapeutiques ne sont pas possibles. Cependant, si votre médecin vous prescrit LORAZEPAM MYLAN 2,5 mg, comprimé pelliculé sécable en même temps que des opioïdes, la posologie et la durée du traitement concomitant doivent être limitées par votre médecin. Veuillez informer votre médecin de tous les médicaments opioïdes que vous prenez et respectez rigoureusement les recommandations posologiques de votre médecin. Il peut être utile d’informer vos amis ou vos parents afin qu’ils soient attentifs aux signes et aux symptômes mentionnés ci-dessus. Contactez votre médecin si vous constatez de tels symptômes. LORAZEPAM MYLAN 2,5 mg, comprimé pelliculé sécable avec des aliments, boissons et de l’alcool Sans objet. Grossesse et allaitement Grossesse Ce médicament est déconseillé pendant la grossesse. Si vous découvrez que vous êtes enceinte ou que vous souhaitez l’être, consultez votre médecin afin qu’il réévalue l’intérêt du traitement. Si vous prenez LORAZEPAM MYLAN au cours du 1 er trimestre de la grossesse : de nombreuses données n’ont pas montré d’effet malformatif des benzodiazépines. Cependant, certaines études ont décrit un risque potentiellement augmenté de survenue de fente labio-palatine chez le nouveau-né par rapport au risque présent dans la population générale. Une fente labio-palatine (parfois nommée « bec de lièvre ») est une malformation congénitale causée par une fusion incomplète du palais et de la lèvre supérieure. Selon ces données, l’incidence des fentes labio-palatines chez les nouveau-nés serait inférieure à 2/1000 après exposition aux benzodiazépines au cours de la grossesse alors que le taux attendu dans la population générale est de 1/1000. Si vous prenez LORAZEPAM MYLAN au 2 ème et/ou 3 ème trimestres de grossesse, une diminution des mouvements actifs fœtaux et une variabilité du rythme cardiaque fœtal peuvent survenir. Si vous prenez LORAZEPAM MYLAN en fin de grossesse, informez en l’équipe médicale, une surveillance du nouveau-né pourrait être effectuée : une faiblesse musculaire (hypotonie axiale), des difficultés d'alimentation (troubles de la succion entrainant une faible prise de poids), une hyperexcitabilité, une agitation ou des tremblements peuvent survenir chez le nouveau-né, ces troubles étant réversibles. A fortes doses, une insuffisance respiratoire ou des apnées, une baisse de la température centrale du corps (hypothermie) pourraient également survenir chez le nouveau-né. Si votre bébé présente un ou plusieurs de ces symptômes à la naissance ou à distance de la naissance, contactez votre médecin et/ou votre sage-femme. Allaitement Ce médicament passe dans le lait maternel : en conséquence, l'allaitement est déconseillé. Demandez conseil à votre médecin ou à votre pharmacien avant de prendre tout médicament. Conduite de véhicules et utilisation de machines L'attention est attirée sur la somnolence et la baisse de la vigilance attachées à l'emploi de ce médicament. L'association avec d'autres médicaments sédatifs ou hypnotiques, et bien entendu avec l'alcool, est déconseillée en cas de conduite automobile ou d'utilisation de machines. Si la durée de sommeil est insuffisante, le risque d'altération de la vigilance est encore accru. LORAZEPAM MYLAN 2,5 mg, comprimé pelliculé sécable contient du lactose et du sodium. Si votre médecin vous a informé(e) d’une intolérance à certains sucres, contactez-le avant de prendre ce médicament. Ce médicament contient moins de 1 mmol (23 mg) de sodium par comprimé, c.-à-d. qu’il est essentiellement « sans sodium ». 3. COMMENT PRENDRE LORAZEPAM MYLAN 2,5 mg, comprimé pelliculé sécable ? Posologie La posologie est strictement individuelle et il n'est pas possible de définir une dose usuelle. Veillez à toujours prendre ce médicament en suivant exactement les instructions de cette notice ou les indications de votre médecin. Vérifiez auprès de votre médecin ou pharmacien en cas de doute Mode et voie d'administration Voie orale. Le comprimé peut être divisé en deux doses égales. Avalez ce médicament avec un verre d'eau. Si vous devez prendre un demi-comprimé, poser le comprimé sur une surface dure, la barre de cassure au-dessus et exercer une pression avec le pouce pour couper le comprimé facilement. Durée du traitement La durée du traitement doit être aussi brève que possible et ne devrait pas dépasser 8 à 12 semaines (voir Mises en garde). Si vous avez pris plus de LORAZEPAM MYLAN 2,5 mg, comprimé pelliculé sécable que vous n’auriez dû Consultez immédiatement votre médecin ou votre pharmacien. Si vous oubliez de prendre LORAZEPAM MYLAN 2,5 mg, comprimé pelliculé sécable Ne prenez pas de dose double pour compenser la dose simple que vous avez oublié de prendre. Prenez la dose suivante à l'heure habituelle. Si vous arrêtez de prendre LORAZEPAM MYLAN 2,5 mg, comprimé pelliculé sécable Phénomènes de sevrage et de rebond ( voir Mises en garde spéciales ). Si vous avez d’autres questions sur l’utilisation de ce médicament, demandez plus d’informations à votre médecin, à votre pharmacien ou à votre infirmier/ère. 4. QUELS SONT LES EFFETS INDESIRABLES EVENTUELS ? Comme tous les médicaments, ce médicament peut provoquer des effets indésirables, mais ils ne surviennent pas systématiquement chez tout le monde. Ils sont en rapport avec la dose ingérée et la sensibilité individuelle du patient. Les effets indésirables suivants ont été rapportés : Très fréquemment (peut concerner plus d’un patient sur 10) · Baisse de vigilance voire somnolence (particulièrement chez le sujet âgé), insomnie. Fréquemment (peut concerner jusqu’à un patient sur 10) · Difficulté à coordonner certains mouvements, confusion, · Faiblesse musculaire, fatigue. Peu fréquemment (peut concerner jusqu’à 1 patient sur 100) · Modifications de la libido. Les effets indésirables suivants, de fréquence indéterminée, ont également été décrits avec le lorazépam : · Troubles de mémoire (trous de mémoire), qui peuvent survenir aux doses thérapeutiques, le risque augmentant proportionnellement à la dose, · Troubles du comportement, modifications de la conscience, irritabilité, agressivité, agitation, · Dépendance physique et psychique, même à doses thérapeutiques avec syndrome de sevrage ou de rebond à l'arrêt du traitement, · Sensations d'ivresse, maux de tête, vertiges, troubles de la prononciation (dysarthrie) et de l'élocution (difficultés à articuler), · Eruptions cutanées avec ou sans démangeaisons. · Vision double, · Réactions d'hypersensibilité, anaphylactiques ou anaphylactoïdes (réaction allergique généralisée pouvant mettre en jeu le pronostic vital), · Hyponatrémie (baisse du sodium dans le sang), · Thrombocytopénie (baisse des plaquettes sanguines), agranulocytose (baisse des globules blancs sanguins), pancytopénie (baisse des globules rouges, des globules blancs et des plaquettes sanguins), · Hallucinations, dépression, idées suicidaires, tentative de suicide, coma, effets extrapyramidaux, tremblements, convulsions, insomnie, cauchemars, tension nerveuse, · Tension artérielle basse (hypotension), · Arrêt de la respiration, dépression respiratoire, aggravation de l’apnée du sommeil, aggravation d’une maladie pulmonaire obstructive, · Mal au cœur (nausées), constipation, · Jaunisse, augmentation de la bilirubine, · Augmentation du taux d’excrétion urinaire (sécrétion inappropriée d’ADH), · Anomalies des paramètres hépatiques (modifications de certains examens biologiques en relation avec une atteinte du foie), · Hypothermie. Déclaration des effets secondaires Si vous ressentez un quelconque effet indésirable, parlez-en à votre médecin, votre pharmacien ou à votre infirmier/ère. Ceci s’applique aussi à tout effet indésirable qui ne serait pas mentionné dans cette notice. Vous pouvez également déclarer les effets indésirables directement via le système national de déclaration : Agence nationale de sécurité du médicament et des produits de santé (ANSM) et réseau des Centres Régionaux de Pharmacovigilance - Site internet : www.signalement-sante.gouv.fr En signalant les effets indésirables, vous contribuez à fournir davantage d’informations sur la sécurité du médicament. 5. COMMENT CONSERVER LORAZEPAM MYLAN 2,5 mg, comprimé pelliculé sécable ? Tenir ce médicament hors de la vue et de la portée des enfants. N’utilisez pas ce médicament après la date de péremption indiquée sur le flacon . La date de péremption fait référence au dernier jour de ce mois. A conserver à une température ne dépassant pas 25°C. Ne jetez aucun médicament au tout-à-l’égout ou avec les ordures ménagères. Demandez à votre pharmacien d’éliminer les médicaments que vous n’utilisez plus. Ces mesures contribueront à protéger l’environnement. 6. CONTENU DE L’EMBALLAGE ET AUTRES INFORMATIONS Ce que contient LORAZEPAM MYLAN 2,5 mg, comprimé pelliculé sécable · La substance active est : Lorazépam........................................................................................................................ 2,500 mg pour un comprimé pelliculé sécable. · Les autres composants sont : Cellulose microcristalline, lactose monohydraté, stéarate de magnésium, copolymère basique de méthacrylate de butyle, talc, jaune de quinoléine, eau purifiée, éthanol 96 %. Qu’est-ce que LORAZEPAM MYLAN 2,5 mg, comprimé pelliculé sécable et contenu de l’emballage extérieur Ce médicament se présente sous forme de comprimé pelliculé sécable. Boîte de 30 comprimés. Titulaire de l’autorisation de mise sur le marché MYLAN SAS 117 ALLEE DES PARCS 69800 SAINT-PRIEST Exploitant de l’autorisation de mise sur le marché MYLAN SAS 117 ALLEE DES PARCS 69800 SAINT-PRIEST Fabricant LABORATOIRES ROTTENDORF PHARMA GMBH OSTENFELDER STRASSE 51-61 59320 ENNIGERLOH ALLEMAGNE OU INPHARMASCI ZI N°2 DE PROUVY-ROUVIGNIES 1 RUE DE NUNGESSER 59121 PROUVY OU MYLAN SAS ZAC DES GAULNES 360 AVENUE HENRI SCHNEIDER 69330 MEYZIEU OU DOPPEL FARMACEUTICI S.R.L. VIA VOLTURNO, 48 QUINTO DE’ STAMPI 20089 ROZZANO ITALIE Noms du médicament dans les Etats membres de l'Espace Economique Européen Sans objet. La dernière date à laquelle cette notice a été révisée est : [à compléter ultérieurement par le titulaire] < {MM/AAAA}>< {mois AAAA}.> Autres Des informations détaillées sur ce médicament sont disponibles sur le site Internet de l’ANSM (France)."
}