{
  "authors": [
    {
      "author": "Mohamed Adnane Berdai"
    },
    {
      "author": " Smael Labib"
    },
    {
      "author": " Monia El Balbal"
    },
    {
      "author": " Mustapha Harandou"
    }
  ],
  "doi": "10.11604/pamj.2011.10.16.1132",
  "publication_date": "2011-10-10",
  "id": "FR100017",
  "url": "https://www.panafrican-med-journal.com/content/article/10/16/full/",
  "source": "The Pan African Medical Journal",
  "source_url": "https://www.panafrican-med-journal.com/",
  "licence": "CC BY 4.0",
  "language": "fr",
  "type": "journal",
  "description": "",
  "text": "Il s’agit d’un enfant de 7 ans, sans antécédents pathologiques notables, victime de piqûres par un essaim d’abeilles intéressant la tête, le visage, le cuir chevelu et les quatre membres occasionnant chez lui des douleurs atroces et des vomissements. Admis une heure trente minutes après l’attaque. L’examen a trouvé un enfant conscient hurlant de douleur, un œdème du cou et de la face comprenant les lèvres, les paupières avec occlusion oculaire complète et le cuir chevelu, apyrétique, tachycarde à 130 b/min, hypertendu à 150/70 mmHg. On a noté la présence d’environ 270 piqûres avec persistance des dards au niveau du cuir chevelu, la face, les oreilles, le thorax et les extrémités des quatre membres. L’enfant a bénéficié d’une oxygénothérapie, trois tests de remplissage par 20 cc/kg de sérum salé isotonique, analgésie par perfusion de paracétamol 15 mg/kg et nalbuphine à raison de 0,05 mg/kg/h, d’où le ralentissement de la fréquence cardiaque, corticothérapie à forte dose à base de méthylprednisolone 2 mg/kg/jour, antiémétiques et antihistaminiques. Par la suite on a procédé à l’ablation des dards avec désinfection cutanée et soins locaux biquotidiens. Le bilan biologique a révélé une hyperleucocytose à 37720 éléments par mm3 à prédominance polynucléaire neutrophile, des CPK-MB à deux fois la valeur normale et une fonction rénale normale initialement. La tomodensitométrie cérébro-orbitaire était normale. L’évolution a été marquée deux jours plus tard par l’apparition d’une conjonctivite d’où sa mise sous antibiothérapie locale (Tobramycine) et par l’installation une anémie hémolytique à 8,2 g/l bien tolérée et une insuffisance rénale (urée: 1,28 g/l, créatinine: 25 mg/l) à diurèse conservé suite à l’hyperhydratation. La fonction rénale s’est corrigée au huitième jour et La régression totale de l’œdème de face a été vers le dixième jour avec comme séquelle un ptosis persistant. La sortie à domicile est faite au 15e jour de son hospitalisation."
}